upp/__init__.py
upp/decode.py
upp/upp.py
upp/atom_gen/__init__.py
upp/atom_gen/atom.py
upp/atom_gen/atombios.py
upp/atom_gen/pptable_v1_0.py
upp/atom_gen/smu_v11_0_7_navi20.py
upp/atom_gen/smu_v11_0_arcturus.py
upp/atom_gen/smu_v11_0_navi10.py
upp/atom_gen/smu_v13_0_7_navi30.py
upp/atom_gen/smu_v14_0_2_navi40.py
upp/atom_gen/vega10_pptable.py
upp/atom_gen/vega20_pptable.py
upp-0.2.4.dist-info/LICENSE
upp-0.2.4.dist-info/METADATA
upp-0.2.4.dist-info/WHEEL
upp-0.2.4.dist-info/entry_points.txt
upp-0.2.4.dist-info/top_level.txt
upp-0.2.4.dist-info/RECORD
